mangabat_dl/__init__.py
mangabat_dl/__main__.py
mangabat_dl/classes.py
mangabat_dl/constants.py
mangabat_dl/downloader.py
mangabat_dl/errors.py
mangabat_dl/fetcher.py
mangabat_dl/utils.py
mangabat_dl-0.0.11.dist-info/LICENSE
mangabat_dl-0.0.11.dist-info/METADATA
mangabat_dl-0.0.11.dist-info/WHEEL
mangabat_dl-0.0.11.dist-info/entry_points.txt
mangabat_dl-0.0.11.dist-info/top_level.txt
mangabat_dl-0.0.11.dist-info/RECORD
