Metadata-Version: 2.1
Name: mangabat-dl
Version: 0.0.11
Summary: Download manga from mangabat with Python
Home-page: https://github.com/mansuf/mangabat-dl
Author: Rahman Yusuf
Author-email: danipart4@gmail.com
License: The Unlicense
Download-URL: https://github.com/mansuf/mangabat-dl/releases
Keywords: mangabat,manga,manga-download
Platform: UNKNOWN
Classifier: Development Status :: 3 - Alpha
Classifier: Intended Audience :: Developers
Classifier: Intended Audience :: End Users/Desktop
Classifier: License :: OSI Approved :: The Unlicense (Unlicense)
Classifier: Programming Language :: Python :: 3
Classifier: Programming Language :: Python :: 3.5
Classifier: Programming Language :: Python :: 3.6
Classifier: Programming Language :: Python :: 3.7
Classifier: Programming Language :: Python :: 3.8
Classifier: Programming Language :: Python :: 3.9
Requires-Python: >=3.5
License-File: LICENSE
Requires-Dist: requests
Requires-Dist: bs4
Requires-Dist: tqdm
